catthy/__init__.py
catthy/definitions.py
catthy/extra.py
catthy/folds.py
catthy/util.py
catthy/applicative/__init__.py
catthy/functor/__init__.py
catthy-0.0.3.1.dist-info/METADATA
catthy-0.0.3.1.dist-info/WHEEL
catthy-0.0.3.1.dist-info/top_level.txt
catthy-0.0.3.1.dist-info/RECORD
