Metadata-Version: 2.1
Name: catthy
Version: 0.0.3.1
Summary: Functional Python library.
Home-page: https://github.com/joangq/catthy
Author: Joan Gonzalez
Author-email: jgquiroga@dc.uba.ar
License: LGPL-3.0
Keywords: functor applicative function
Platform: UNKNOWN
Classifier: Development Status :: 1 - Planning
Requires-Python: >=3.7
